autodiff_team44/__init__.py
autodiff_team44/ad.py
autodiff_team44/functions.py
autodiff_team44/rev_ad.py
autodiff_team44/rev_variable.py
autodiff_team44/variable.py
autodiff_team44-0.1.0.dist-info/LICENSE
autodiff_team44-0.1.0.dist-info/METADATA
autodiff_team44-0.1.0.dist-info/WHEEL
autodiff_team44-0.1.0.dist-info/top_level.txt
autodiff_team44-0.1.0.dist-info/RECORD
